README.md
setup.cfg
setup.py
BertLibrary/__init__.py
BertLibrary/bert_evaluator.py
BertLibrary/bert_predictor.py
BertLibrary/bert_trainer.py
BertLibrary.egg-info/PKG-INFO
BertLibrary.egg-info/SOURCES.txt
BertLibrary.egg-info/dependency_links.txt
BertLibrary.egg-info/requires.txt
BertLibrary.egg-info/top_level.txt
BertLibrary/bert/__init__.py
BertLibrary/bert/create_pretraining_data.py
BertLibrary/bert/extract_features.py
BertLibrary/bert/modeling.py
BertLibrary/bert/modeling_test.py
BertLibrary/bert/optimization.py
BertLibrary/bert/optimization_test.py
BertLibrary/bert/run_classifier.py
BertLibrary/bert/run_classifier_with_tfhub.py
BertLibrary/bert/run_pretraining.py
BertLibrary/bert/run_squad.py
BertLibrary/bert/tokenization.py
BertLibrary/bert/tokenization_test.py
BertLibrary/models/BertFEModel.py
BertLibrary/models/BertFTModel.py
BertLibrary/models/BertModel.py
BertLibrary/models/__init__.py
BertLibrary/processors/FEProcessor.py
BertLibrary/processors/FTProcessor.py
BertLibrary/processors/Label2TextProcessor.py
BertLibrary/processors/Processor.py
BertLibrary/processors/__init__.py